vnpy_sinopac/__init__.py
vnpy_sinopac/gateway/__init__.py
vnpy_sinopac/gateway/sinopac_gateway.py
vnpy_sinopac-4.0.4.dist-info/METADATA
vnpy_sinopac-4.0.4.dist-info/WHEEL
vnpy_sinopac-4.0.4.dist-info/licenses/LICENSE
vnpy_sinopac-4.0.4.dist-info/RECORD
