Metadata-Version: 2.4
Name: vnpy_sinopac
Version: 4.0.4
Summary: Sinopac Securities - Shioaji api gateway for VeighNa quant trading framework.
Project-URL: Documentation, https://sinotrade.github.io/
Project-URL: Release notes, https://sinotrade.github.io/release/
Project-URL: Funding, https://sjapi.tw
Project-URL: Source, https://github.com/ypochien/vnpy_sinopac
Project-URL: Homepage, https://github.com/ypochien/vnpy_sinopac
Author-email: ypochien <ypochien@gmail.com>
License: MIT
License-File: LICENSE
Keywords: algotrading,investment,quant,quantitative,trading
Classifier: Development Status :: 4 - Beta
Classifier: License :: OSI Approved :: MIT License
Classifier: Natural Language :: Chinese (Traditional)
Classifier: Operating System :: MacOS
Classifier: Operating System :: Microsoft :: Windows
Classifier: Operating System :: POSIX
Classifier: Operating System :: Unix
Classifier: Programming Language :: Python :: 3
Classifier: Programming Language :: Python :: 3.10
Classifier: Programming Language :: Python :: 3.11
Classifier: Programming Language :: Python :: 3.12
Classifier: Programming Language :: Python :: 3.13
Classifier: Programming Language :: Python :: Implementation :: CPython
Classifier: Topic :: Office/Business :: Financial :: Investment
Requires-Python: <3.14,>=3.10
Requires-Dist: importlib-metadata
Requires-Dist: polars>=0.20.0
Requires-Dist: shioaji>=1.0.0
Requires-Dist: wmi; sys_platform == 'win32'
Provides-Extra: dev
Requires-Dist: black>=22.1.0; extra == 'dev'
Requires-Dist: isort>=5.10.1; extra == 'dev'
Requires-Dist: pygments>=2.0.0; extra == 'dev'
Requires-Dist: pytest>=7.0.1; extra == 'dev'
Provides-Extra: test
Requires-Dist: pygments>=2.0.0; extra == 'test'
Requires-Dist: pytest>=7.0.1; extra == 'test'
